{
  "source": "setopati",
  "url": "https://www.setopati.com/social/389596",
  "title": "तस्बिरमा हेर्नुहोस् नेपालमै पहिलो पटक भएको मुटुको भल्ब फेर्ने 'वेट ल्याब'",
  "published_at": null,
  "scraped_at": "2026-05-23T08:32:53.022602",
  "authors": [],
  "summary": "",
  "content": "नेपालमै पहिलो पटक मुटुको भल्ब प्रत्यारोपणसम्बन्धी 'वेट ल्याब' सञ्चालन गरिएको छ। त्रिभुवन विश्वविध्यालय अन्तर्गतको मनमोहन कार्डियोथोरासिक भास्कुलर एन्ड ट्रान्सप्लान्ट सेन्टरमा आयोजित उक्त कार्यक्रमले नेपालमा मुटु शल्यचिकित्सा प्रशिक्षणको नयाँ अध्याय सुरू गरेको चिकित्सकहरुले बताएका छन्। कार्यक्रमको नेतृत्व केन्द्रको कार्डियोथोरासिक तथा भास्कुलर सर्जरी (सिटीभिएस) विभागका विभागीय प्रमुख डा. अनिल भट्टराईले गरेका थिए। उनका अनुसार, यो वेट ल्याबको मुख्य उद्देश्य नयाँ पुस्ताका मुटु शल्यचिकित्सकहरुलाई मुटुको भल्ब फेर्ने आधुनिक प्रविधिबारे व्यावहारिक प्रशिक्षण दिनु हो। कार्यक्रममा एमसिएच अध्ययनरत ६ जना चिकित्सक र एक जना रजिस्ट्रारसहित सात जना चिकित्सक सहभागी भएका थिए। उनीहरूले मानव शरीरमा प्रयोग गरिने वास्तविक मुटुको भल्ब नै प्रयोग गरेर अभ्यास गरेका थिए। यद्यपि ती भल्बहरू म्याद नाघिसकेका अर्थात् बिरामीमा प्रयोग गर्न नमिल्ने भल्बहरू हुन्। यसबाट प्रशिक्षार्थीहरूले वास्तविक शल्यक्रियामा जस्तै वातावरणमा अभ्यास गर्ने अवसर पाए। सामान्यतया प्रशिक्षार्थी चिकित्सकहरूले अपरेसन थिएटरमा वरिष्ठ चिकित्सकले गरेको शल्यक्रिया हेरेर सिक्ने गर्छन्। यस्तो वेट ल्याबमा भने आफ्नै हातले सम्पूर्ण प्रक्रिया अभ्यास गर्न पाउने भएकाले सिकाइ अझ प्रभावकारी हुने विश्वास गरिएको छ। डा. भट्टराइले आफूले विदेशमा अध्ययन गर्दा यस्ता तालिम देखेको र गरेको अनुभव सुनाउँदै नेपालमा पनि त्यही अभ्यास सुरू गर्न चाहेको बताए। यसले युवा चिकित्सकमा मुटु शल्यचिकित्साप्रति आकर्षण बढाउने मात्र होइन, दक्ष जनशक्ति उत्पादनमा समेत ठूलो योगदान पुर्‍याउने उनको भनाइ छ। कार्यक्रमको उद्घाटन इन्स्टिच्युट अफ मेडिसिनका डिन डा. मोहनराज शर्माले गरेका थिए। कार्यक्रममा शिक्षण अस्पताल, मनमोहन सेन्टर, आयु सेन्टर तथा महाराजगन्ज मेडिकल क्याम्पसका पदाधिकारी र विभिन्न अस्पतालका मुटु शल्यचिकित्सकहरूको उपस्थिति थियो। नेपालका विभिन्न अस्पतालमा मुटु शल्यचिकित्सामा संलग्न चिकित्सकहरूलाई एउटै मञ्चमा ल्याएर गरिएको यो अभ्यासलाई सहभागीहरूले ऐतिहासिक सुरूआतका रूपमा लिएका छन्। आयोजक विभागले भविष्यमा पनि यस्ता तालिममूलक कार्यक्रमलाई निरन्तरता दिने जनाएको छ।\n\nनेपालमै पहिलो पटक मुटुको भल्ब प्रत्यारोपणसम्बन्धी 'वेट ल्याब' सञ्चालन गरिएको छ। त्रिभुवन विश्वविध्यालय अन्तर्गतको मनमोहन कार्डियोथोरासिक भास्कुलर एन्ड ट्रान्सप्लान्ट सेन्टरमा आयोजित उक्त कार्यक्रमले नेपालमा मुटु शल्यचिकित्सा प्रशिक्षणको नयाँ अध्याय सुरू गरेको चिकित्सकहरुले बताएका छन्। कार्यक्रमको नेतृत्व केन्द्रको कार्डियोथोरासिक तथा भास्कुलर सर्जरी (सिटीभिएस) विभागका विभागीय प्रमुख डा. अनिल भट्टराईले गरेका थिए। उनका अनुसार, यो वेट ल्याबको मुख्य उद्देश्य नयाँ पुस्ताका मुटु शल्यचिकित्सकहरुलाई मुटुको भल्ब फेर्ने आधुनिक प्रविधिबारे व्यावहारिक प्रशिक्षण दिनु हो। कार्यक्रममा एमसिएच अध्ययनरत ६ जना चिकित्सक र एक जना रजिस्ट्रारसहित सात जना चिकित्सक सहभागी भएका थिए। उनीहरूले मानव शरीरमा प्रयोग गरिने वास्तविक मुटुको भल्ब नै प्रयोग गरेर अभ्यास गरेका थिए। यद्यपि ती भल्बहरू म्याद नाघिसकेका अर्थात् बिरामीमा प्रयोग गर्न नमिल्ने भल्बहरू हुन्। यसबाट प्रशिक्षार्थीहरूले वास्तविक शल्यक्रियामा जस्तै वातावरणमा अभ्यास गर्ने अवसर पाए। सामान्यतया प्रशिक्षार्थी चिकित्सकहरूले अपरेसन थिएटरमा वरिष्ठ चिकित्सकले गरेको शल्यक्रिया हेरेर सिक्ने गर्छन्। यस्तो वेट ल्याबमा भने आफ्नै हातले सम्पूर्ण प्रक्रिया अभ्यास गर्न पाउने भएकाले सिकाइ अझ प्रभावकारी हुने विश्वास गरिएको छ। डा. भट्टराइले आफूले विदेशमा अध्ययन गर्दा यस्ता तालिम देखेको र गरेको अनुभव सुनाउँदै नेपालमा पनि त्यही अभ्यास सुरू गर्न चाहेको बताए। यसले युवा चिकित्सकमा मुटु शल्यचिकित्साप्रति आकर्षण बढाउने मात्र होइन, दक्ष जनशक्ति उत्पादनमा समेत ठूलो योगदान पुर्‍याउने उनको भनाइ छ। कार्यक्रमको उद्घाटन इन्स्टिच्युट अफ मेडिसिनका डिन डा. मोहनराज शर्माले गरेका थिए। कार्यक्रममा शिक्षण अस्पताल, मनमोहन सेन्टर, आयु सेन्टर तथा महाराजगन्ज मेडिकल क्याम्पसका पदाधिकारी र विभिन्न अस्पतालका मुटु शल्यचिकित्सकहरूको उपस्थिति थियो। नेपालका विभिन्न अस्पतालमा मुटु शल्यचिकित्सामा संलग्न चिकित्सकहरूलाई एउटै मञ्चमा ल्याएर गरिएको यो अभ्यासलाई सहभागीहरूले ऐतिहासिक सुरूआतका रूपमा लिएका छन्। आयोजक विभागले भविष्यमा पनि यस्ता तालिममूलक कार्यक्रमलाई निरन्तरता दिने जनाएको छ।\n\nनेपालमै पहिलो पटक मुटुको भल्ब प्रत्यारोपणसम्बन्धी 'वेट ल्याब' सञ्चालन गरिएको छ।\n\nत्रिभुवन विश्वविध्यालय अन्तर्गतको मनमोहन कार्डियोथोरासिक भास्कुलर एन्ड ट्रान्सप्लान्ट सेन्टरमा आयोजित उक्त कार्यक्रमले नेपालमा मुटु शल्यचिकित्सा प्रशिक्षणको नयाँ अध्याय सुरू गरेको चिकित्सकहरुले बताएका छन्।\n\nकार्यक्रमको नेतृत्व केन्द्रको कार्डियोथोरासिक तथा भास्कुलर सर्जरी (सिटीभिएस) विभागका विभागीय प्रमुख डा. अनिल भट्टराईले गरेका थिए।\n\nउनका अनुसार, यो वेट ल्याबको मुख्य उद्देश्य नयाँ पुस्ताका मुटु शल्यचिकित्सकहरुलाई मुटुको भल्ब फेर्ने आधुनिक प्रविधिबारे व्यावहारिक प्रशिक्षण दिनु हो।\n\nकार्यक्रममा एमसिएच अध्ययनरत ६ जना चिकित्सक र एक जना रजिस्ट्रारसहित सात जना चिकित्सक सहभागी भएका थिए।\n\nउनीहरूले मानव शरीरमा प्रयोग गरिने वास्तविक मुटुको भल्ब नै प्रयोग गरेर अभ्यास गरेका थिए। यद्यपि ती भल्बहरू म्याद नाघिसकेका अर्थात् बिरामीमा प्रयोग गर्न नमिल्ने भल्बहरू हुन्। यसबाट प्रशिक्षार्थीहरूले वास्तविक शल्यक्रियामा जस्तै वातावरणमा अभ्यास गर्ने अवसर पाए।\n\nसामान्यतया प्रशिक्षार्थी चिकित्सकहरूले अपरेसन थिएटरमा वरिष्ठ चिकित्सकले गरेको शल्यक्रिया हेरेर सिक्ने गर्छन्। यस्तो वेट ल्याबमा भने आफ्नै हातले सम्पूर्ण प्रक्रिया अभ्यास गर्न पाउने भएकाले सिकाइ अझ प्रभावकारी हुने विश्वास गरिएको छ।\n\nडा. भट्टराइले आफूले विदेशमा अध्ययन गर्दा यस्ता तालिम देखेको र गरेको अनुभव सुनाउँदै नेपालमा पनि त्यही अभ्यास सुरू गर्न चाहेको बताए।\n\nयसले युवा चिकित्सकमा मुटु शल्यचिकित्साप्रति आकर्षण बढाउने मात्र होइन, दक्ष जनशक्ति उत्पादनमा समेत ठूलो योगदान पुर्‍याउने उनको भनाइ छ।\n\nकार्यक्रमको उद्घाटन इन्स्टिच्युट अफ मेडिसिनका डिन डा. मोहनराज शर्माले गरेका थिए।\n\nकार्यक्रममा शिक्षण अस्पताल, मनमोहन सेन्टर, आयु सेन्टर तथा महाराजगन्ज मेडिकल क्याम्पसका पदाधिकारी र विभिन्न अस्पतालका मुटु शल्यचिकित्सकहरूको उपस्थिति थियो।\n\nनेपालका विभिन्न अस्पतालमा मुटु शल्यचिकित्सामा संलग्न चिकित्सकहरूलाई एउटै मञ्चमा ल्याएर गरिएको यो अभ्यासलाई सहभागीहरूले ऐतिहासिक सुरूआतका रूपमा लिएका छन्।\n\nआयोजक विभागले भविष्यमा पनि यस्ता तालिममूलक कार्यक्रमलाई निरन्तरता दिने जनाएको छ।",
  "main_image": "https://www.setopati.com/uploads/posts/mutu-operation--(11)-1779447324.jpg",
  "image_urls": [
    "https://www.setopati.com/uploads/posts/mutu-operation--(11)-1779447324.jpg",
    "https://www.setopati.com/uploads/posts/mutu-operation--(11)-1779447324.jpg",
    "https://www.facebook.com/tr?id=145457993056440&ev=PageView\n&noscript=1",
    "https://www.setopati.com/themes/setopati/images/logo.svg?v=1.9",
    "https://www.setopati.com/themes/setopati/images/logo-icon.svg",
    "https://www.setopati.com/themes/setopati/images/adsthumb/rectangle.png",
    "https://www.setopati.com/uploads/posts/mutu-operation--(5)-1779447323.jpg",
    "https://www.setopati.com/uploads/posts/mutu-operation--(7)-1779447324.jpg",
    "https://www.setopati.com/uploads/posts/mutu-operation--(8)-1779447324.jpg",
    "https://www.setopati.com/uploads/posts/mutu-operation--(9)-1779447324.jpg",
    "https://www.setopati.com/uploads/posts/mutu-operation--(10)-1779447324.jpg",
    "https://www.setopati.com/uploads/posts/mutu-operation--(12)-1779447324.jpg",
    "https://www.setopati.com/uploads/posts/mutu-operation--(1)-1779447323.jpg",
    "https://www.setopati.com/uploads/posts/mutu-operation--(2)-1779447323.jpg",
    "https://www.setopati.com/uploads/posts/mutu-operation--(3)-1779447323.jpg",
    "https://www.setopati.com/uploads/posts/mutu-operation--(4)-1779447323.jpg",
    "https://www.setopati.com/uploads/posts/mutu-operation--(6)-1779447323.jpg"
  ],
  "tags": [
    "तस्बिरमा, हेर्नुहोस्, नेपालमै, पहिलो, पटक, भएको, मुटुको, भल्ब, फेर्ने, 'वेट, ल्याब', नवीनबाबु गुरूङ, Setopati"
  ],
  "language": "ne",
  "meta": {
    "og:title": "तस्बिरमा हेर्नुहोस् नेपालमै पहिलो पटक भएको मुटुको भल्ब फेर्ने 'वेट ल्याब'",
    "og:url": "https://www.setopati.com/social/389596/",
    "og:description": "उनीहरूले मानव शरीरमा प्रयोग गरिने वास्तविक मुटुको भल्ब नै प्रयोग गरेर अभ्यास गरेका हुन्।",
    "og:image": "https://www.setopati.com/uploads/posts/mutu-operation--(11)-1779447324.jpg",
    "og:type": "article",
    "og:site_name ": "Setopati",
    "twitter:card": "summary_large_image",
    "twitter:site": "@setopati",
    "twitter:title": "तस्बिरमा हेर्नुहोस् नेपालमै पहिलो पटक भएको मुटुको भल्ब फेर्ने 'वेट ल्याब'",
    "twitter:description": "उनीहरूले मानव शरीरमा प्रयोग गरिने वास्तविक मुटुको भल्ब नै प्रयोग गरेर अभ्यास गरेका हुन्।",
    "twitter:image": "https://www.setopati.com/uploads/posts/mutu-operation--(11)-1779447324.jpg",
    "keywords": "तस्बिरमा, हेर्नुहोस्, नेपालमै, पहिलो, पटक, भएको, मुटुको, भल्ब, फेर्ने, 'वेट, ल्याब', नवीनबाबु गुरूङ, Setopati",
    "author": "नवीनबाबु गुरूङ :: Setopati"
  }
}